[
    {
        "title": "WalkBuddy",
        "videoSrc": "projects/walkbuddy.mp4",
        "imageSrc": "projects/walkbuddy.JPG",
        "description": "WalkBuddy verbindet Hundebesitzer in deiner Nähe für gemeinsame Spaziergänge.",
        "skills": ["React", "Node", "Typescript", "Express", "SQLite","Chakra UI"],
        "demo": "https://walk-buddy.app//"
    },
    {
        "title": "TeamToss",
        "videoSrc": "projects/teamTossPreview.mp4",
        "imageSrc": "projects/teamTossPreview.jpg",
        "description": "TeamToss - Der Teamgenerator",
        "skills": ["React", "Node", "Typescript", "Firebase"],
        "demo": "https://teamtoss.vercel.app/"
    }
   
]
